{"1c_collections_page_001.md":"_vpGbixC","1c_page_001.md":"Cv7ZQafb","1c_page_002.md":"DoOFyq2I","1c_syntax_page_001.md":"CNPoItp7","1c_syntax_page_002.md":"D8OS0Chi","1c_syntax_page_003.md":"DX_05ikc","1c_syntax_page_004.md":"CU5pyUsh","1c_syntax_page_005.md":"1hxY8jAj","1c_syntax_page_006.md":"DewkznTl","1c_syntax_page_007.md":"C4XImQ2n","1c_syntax_page_008.md":"udMLOhbs","1c_syntax_page_009.md":"Bnz2WsPm","1c_syntax_page_010.md":"C4kWSS46","1c_syntax_page_011.md":"CsPobQTl","1c_syntax_page_012.md":"C97OZreZ","1c_syntax_page_013.md":"DIzBsk-d","css_animation_page_001.md":"B0qcerk9","css_animation_page_002.md":"CoVf00-7","css_animation_page_003.md":"CCkyd8HR","css_layout_page_001.md":"BXlPLmIx","css_layout_page_002.md":"CrJNqWrJ","css_layout_page_003.md":"BMFxKh34","css_layout_page_004.md":"CqoKPk49","css_layout_page_005.md":"C8p1HB5K","css_layout_page_006.md":"xyz71O3W","css_layout_page_007.md":"i4wUHx4L","css_layout_page_008.md":"Dd1Lf7Gw","css_layout_page_009.md":"BpzSGaYk","css_page_001.md":"CZAbLMOh","css_page_002.md":"BZ_1fnrP","css_property_page_001.md":"DieGu8Ej","css_property_page_002.md":"DRVpiFIU","css_property_page_003.md":"DAStrqD3","css_property_page_004.md":"CFXdLN1j","css_property_page_005.md":"kfhMP-Jc","css_property_page_006.md":"DJ5mDv-n","css_property_page_007.md":"Clxh9Sdw","css_property_page_008.md":"Jc7HjbBG","css_property_page_009.md":"125_-sF9","css_property_page_010.md":"C4vNkpbt","css_property_page_011.md":"CHaqbk1O","css_property_page_012.md":"Bd7GqQEY","css_property_page_013.md":"C-wO8AIc","css_property_page_014.md":"B0BnI6rJ","css_selectors_page_001.md":"C8vh1YuW","css_selectors_page_002.md":"BfdUuqcs","css_selectors_page_003.md":"Cbgu8Y3H","css_selectors_page_004.md":"ag7F4WPj","css_selectors_page_005.md":"CCTaNkDx","css_selectors_page_006.md":"BN4h9lJe","css_selectors_page_007.md":"DLnmQEUW","gsap_page_001.md":"-M4wnMA3","html_elements_page_001.md":"3K9SDl7w","html_elements_page_002.md":"DppyweRx","html_elements_page_003.md":"BczQQnjW","html_elements_page_004.md":"C5i2gsDM","html_elements_page_005.md":"CKU9OVA6","html_elements_page_006.md":"CO9nXSv7","html_elements_page_007.md":"BQ33MkIr","html_elements_page_008.md":"Cgvdf1Xt","html_elements_page_009.md":"OjIs3-MO","html_forms_page_001.md":"DqYJUPg3","html_forms_page_002.md":"CSNFN5TB","html_page_001.md":"Q8tdXeQQ","html_page_005.md":"C_0Ajo9l","html_semantic_page_001.md":"DFGmwaMg","html_semantic_page_002.md":"B8Y5R-Gr","index.md":"CC64kJfk","jest_page_001.md":"CeAdpfr3","jest_page_002.md":"CBzQmer9","python_page_001.md":"B9Zou6r4","python_page_002.md":"4Zebm5HM","rust_page_001.md":"BNc83sZK","socketio_page_001.md":"CYgVslpK","swagger_page_001.md":"C6-AZ0XP","tests_page_001.md":"C6Sugory","updates_2025_06-june.md":"ChS19Ebc","updates_2025_07-july.md":"C7gfvfoN","videos_page_001.md":"C4ZLe5Yy","vitepress_page_001.md":"C7AHzvr8"}
