{"1c_collections_page_001.md":"DUQr8MRH","1c_page_001.md":"C0ITOCPs","1c_page_002.md":"DhPKiTgm","1c_syntax_page_001.md":"BK3klJx2","1c_syntax_page_002.md":"CfQ2-6XA","1c_syntax_page_003.md":"k_Obu2FN","1c_syntax_page_004.md":"nNL_5k29","1c_syntax_page_005.md":"CBiuRR23","1c_syntax_page_006.md":"BcHq82CC","1c_syntax_page_007.md":"yF0hdBay","1c_syntax_page_008.md":"D_a4_tkc","1c_syntax_page_009.md":"D9wHWXp2","1c_syntax_page_010.md":"D5r-ky2V","1c_syntax_page_011.md":"BlODwJH5","1c_syntax_page_012.md":"CooOX4fK","1c_syntax_page_013.md":"CZDn5vje","courses.md":"DkvBppOU","courses_cypress_page_001.md":"CPxvJM1z","courses_htmx_page_001.md":"DbQGdbAE","css_animation_page_001.md":"Cmw3x8e5","css_animation_page_002.md":"CKFfGu_z","css_animation_page_003.md":"BJaZ2Rrc","css_layout_page_001.md":"Cd8cIAz6","css_layout_page_002.md":"DrYAI4bU","css_layout_page_003.md":"BOmY-Ves","css_layout_page_004.md":"15Xyi-AS","css_layout_page_005.md":"r35kkvvB","css_layout_page_006.md":"DJvdCrYT","css_layout_page_007.md":"6NrHo76_","css_layout_page_008.md":"DF90LHym","css_layout_page_009.md":"BXb8JpQS","css_page_001.md":"C7F5AC6q","css_page_002.md":"Bey_Ty2t","css_property_page_001.md":"tF-Efzj6","css_property_page_002.md":"D311GUvz","css_property_page_003.md":"B_ixoEma","css_property_page_004.md":"BLJzikfS","css_property_page_005.md":"CFKKh05O","css_property_page_006.md":"DyoZfGe0","css_property_page_007.md":"D6F1IfkJ","css_property_page_008.md":"DivkATUp","css_property_page_009.md":"CzGmnmfv","css_property_page_010.md":"BmlRPyMz","css_property_page_011.md":"C2gNrrdc","css_property_page_012.md":"djSyzn1J","css_property_page_013.md":"B5set_pg","css_property_page_014.md":"D9XLyOZn","css_selectors_page_001.md":"CLJgkqNP","css_selectors_page_002.md":"DrKGQNim","css_selectors_page_003.md":"DN8ZOFFC","css_selectors_page_004.md":"B1V34-hx","css_selectors_page_005.md":"ClNGkHXb","css_selectors_page_006.md":"gsRt3mSO","css_selectors_page_007.md":"DhRTi6ia","gsap_page_001.md":"BT24IpDC","html_elements_page_001.md":"Byy2USMR","html_elements_page_002.md":"OZr1a2f3","html_elements_page_003.md":"Vpdy02RU","html_elements_page_004.md":"DYEYBmXc","html_elements_page_005.md":"DyAXCXlI","html_elements_page_006.md":"J1zNOVMm","html_elements_page_007.md":"CUwlD3lA","html_elements_page_008.md":"Bh2j16Ua","html_elements_page_009.md":"DZTWM2eY","html_forms_page_001.md":"Cr4aFaTb","html_forms_page_002.md":"BKnRgVPW","html_page_001.md":"Cw7AzzHg","html_page_005.md":"Bv2pPJN9","html_semantic_page_001.md":"2Br3Hi1E","html_semantic_page_002.md":"BVSF_23s","index.md":"5zUtxiPy","jest_page_001.md":"3IqhmREX","jest_page_002.md":"ZvA-tNWa","python_page_001.md":"B4awHEmM","python_page_002.md":"DBlrUDij","rust_page_001.md":"O53hTFBN","socketio_page_001.md":"0-NCKxtT","swagger_page_001.md":"D-etNgIO","tests_page_001.md":"9xDmy6gH","updates_2025_06-june.md":"DDVR48zM","updates_2025_07-july.md":"BT0Atb5r","updates_2025_08-august.md":"DIs5nE2x","updates_2025_09-september.md":"3Qo0UvIj","updates_2025_10-october.md":"x82qZdir","videos_page_001.md":"AdmRjkQv","vitepress_page_001.md":"D58VZvQt"}
