{"1c_collections_page_001.md":"DUhg3Bdq","1c_page_001.md":"CoOXWtv1","1c_page_002.md":"CLoumyDm","1c_syntax_page_001.md":"BWJuXxE4","1c_syntax_page_002.md":"Cw0OvOYT","1c_syntax_page_003.md":"BjgG-FF1","1c_syntax_page_004.md":"B4TYE_Lt","1c_syntax_page_005.md":"poZbDIkM","1c_syntax_page_006.md":"mzD3Oo1j","1c_syntax_page_007.md":"DCTK32eY","1c_syntax_page_008.md":"Hu13fvQP","1c_syntax_page_009.md":"DnKsTMH4","1c_syntax_page_010.md":"BBUhcsKd","1c_syntax_page_011.md":"DslLm36A","1c_syntax_page_012.md":"Cib1EBtN","1c_syntax_page_013.md":"BLP35hbe","courses_cypress_maximilian-schwarzmuller.md":"DPpgeRBW","courses_go_maximilian-schwarzmuller.md":"bTtCY9F7","courses_htmx_maximilian-schwarzmuller.md":"Cbd6_vjJ","courses_linux_colt-steele.md":"Bl7vtUNV","courses_os_hussein-nasser.md":"r7gJI2jX","css_animation_page_001.md":"zgLIFTef","css_animation_page_002.md":"gBUS4_FS","css_animation_page_003.md":"De2AV9c4","css_layout_page_001.md":"BD5-Q8xo","css_layout_page_002.md":"CcihhUvB","css_layout_page_003.md":"BNApnUhw","css_layout_page_004.md":"BaGs_i7f","css_layout_page_005.md":"DuniakVs","css_layout_page_006.md":"BhyFZ5f5","css_layout_page_007.md":"CIeJyxNI","css_layout_page_008.md":"Rbc2hVrs","css_layout_page_009.md":"BFTG5jTe","css_page_001.md":"DIus-u2G","css_page_002.md":"b6G6NYdI","css_property_page_001.md":"sctTy1Uy","css_property_page_002.md":"C-ztQvKJ","css_property_page_003.md":"BVrLn95Z","css_property_page_004.md":"De2O6VFx","css_property_page_005.md":"BTeuMpB0","css_property_page_006.md":"B5yu1533","css_property_page_007.md":"By65CWJu","css_property_page_008.md":"DmTU0JU2","css_property_page_009.md":"CReGHppG","css_property_page_010.md":"DG8aindg","css_property_page_011.md":"Bu1Q04gf","css_property_page_012.md":"XrNz07ty","css_property_page_013.md":"D07uOdTG","css_property_page_014.md":"vh17nIF2","css_selectors_page_001.md":"ozebd3eO","css_selectors_page_002.md":"DbJNi-e5","css_selectors_page_003.md":"4VbSNO3T","css_selectors_page_004.md":"BlFie5b7","css_selectors_page_005.md":"Bt6-9IFS","css_selectors_page_006.md":"3O7Gc4Fx","css_selectors_page_007.md":"CBWTf23A","gsap_page_001.md":"B-oOJjcT","html_elements_page_001.md":"r-TdlBXC","html_elements_page_002.md":"DXBdwNiT","html_elements_page_003.md":"pNvMyg92","html_elements_page_004.md":"HyckGhF5","html_elements_page_005.md":"DqjqL37u","html_elements_page_006.md":"B9CLpPnu","html_elements_page_007.md":"WVf4-RzS","html_elements_page_008.md":"CiTsJrhQ","html_elements_page_009.md":"Cd9efpqJ","html_forms_page_001.md":"BlQHru7C","html_forms_page_002.md":"D9B_xPA4","html_page_001.md":"DE9V-Fkr","html_page_005.md":"DbyZI-vO","html_semantic_page_001.md":"DvOl_8DE","html_semantic_page_002.md":"DVxhaXca","index.md":"Dwqn-whE","jest_page_001.md":"al8-wgaT","jest_page_002.md":"C1GmeXy9","python_page_001.md":"Mx-ykL1d","python_page_002.md":"C0g-ygmr","road-map.md":"3Kepkvis","rust_page_001.md":"Brs6G7ZE","socketio_page_001.md":"CYLJ0j5j","swagger_page_001.md":"C_Ox9NWz","tests_page_001.md":"BCJZ4fkI","updates_2025_06-june.md":"Cn5O3ysV","updates_2025_07-july.md":"DQ-u50Dw","updates_2025_08-august.md":"C2-8quLE","updates_2025_09-september.md":"D6blFuL5","updates_2025_10-october.md":"Dx7gyUzi","updates_2025_11-november.md":"NpCJ93lX","videos_page_001.md":"DYwZXf08","vitepress_page_001.md":"C1pNcUfh"}
